{
  "annotations": {
    "list": [
      {
        "builtIn": 1,
        "datasource": {
          "type": "grafana",
          "uid": "-- Grafana --"
        },
        "enable": true,
        "hide": true,
        "iconColor": "rgba(0, 211, 255, 1)",
        "name": "Annotations & Alerts",
        "type": "dashboard"
      }
    ]
  },
  "editable": true,
  "fiscalYearStartMonth": 0,
  "graphTooltip": 0,
  "id": null,
  "links": [],
  "panels": [
    {
      "datasource": {
        "type": "prometheus",
        "uid": "prometheus"
      },
      "fieldConfig": {
        "defaults": {
          "color": {
            "mode": "thresholds"
          },
          "mappings": [],
          "thresholds": {
            "mode": "absolute",
            "steps": [
              {
                "color": "green",
                "value": null
              }
            ]
          },
          "unit": "reqps"
        },
        "overrides": []
      },
      "gridPos": {
        "h": 6,
        "w": 6,
        "x": 0,
        "y": 0
      },
      "id": 1,
      "options": {
        "colorMode": "value",
        "graphMode": "area",
        "justifyMode": "auto",
        "orientation": "auto",
        "reduceOptions": {
          "calcs": [
            "lastNotNull"
          ],
          "fields": "",
          "values": false
        },
        "showPercentChange": false,
        "textMode": "auto",
        "wideLayout": true
      },
      "pluginVersion": "11.4.0",
      "targets": [
        {
          "expr": "sum(rate(aegismesh_http_requests_total[5m]))",
          "legendFormat": "requests/sec",
          "refId": "A"
        }
      ],
      "title": "Backend Request Rate",
      "type": "stat"
    },
    {
      "datasource": {
        "type": "prometheus",
        "uid": "prometheus"
      },
      "fieldConfig": {
        "defaults": {
          "color": {
            "mode": "thresholds"
          },
          "mappings": [],
          "thresholds": {
            "mode": "absolute",
            "steps": [
              {
                "color": "green",
                "value": null
              },
              {
                "color": "red",
                "value": 1
              }
            ]
          },
          "unit": "reqps"
        },
        "overrides": []
      },
      "gridPos": {
        "h": 6,
        "w": 6,
        "x": 6,
        "y": 0
      },
      "id": 2,
      "options": {
        "colorMode": "value",
        "graphMode": "area",
        "justifyMode": "auto",
        "orientation": "auto",
        "reduceOptions": {
          "calcs": [
            "lastNotNull"
          ],
          "fields": "",
          "values": false
        },
        "showPercentChange": false,
        "textMode": "auto",
        "wideLayout": true
      },
      "pluginVersion": "11.4.0",
      "targets": [
        {
          "expr": "sum(rate(aegismesh_http_requests_total{status_code=~\"5..\"}[5m]))",
          "legendFormat": "5xx/sec",
          "refId": "A"
        }
      ],
      "title": "Backend Error Rate",
      "type": "stat"
    },
    {
      "datasource": {
        "type": "prometheus",
        "uid": "prometheus"
      },
      "fieldConfig": {
        "defaults": {
          "color": {
            "mode": "palette-classic"
          },
          "custom": {
            "axisBorderShow": false,
            "axisCenteredZero": false,
            "axisColorMode": "text",
            "axisLabel": "",
            "axisPlacement": "auto",
            "barAlignment": 0,
            "drawStyle": "line",
            "fillOpacity": 10,
            "gradientMode": "none",
            "hideFrom": {
              "legend": false,
              "tooltip": false,
              "viz": false
            },
            "insertNulls": false,
            "lineInterpolation": "linear",
            "lineWidth": 2,
            "pointSize": 5,
            "scaleDistribution": {
              "type": "linear"
            },
            "showPoints": "never",
            "spanNulls": false,
            "stacking": {
              "group": "A",
              "mode": "none"
            },
            "thresholdsStyle": {
              "mode": "off"
            }
          },
          "mappings": [],
          "unit": "s"
        },
        "overrides": []
      },
      "gridPos": {
        "h": 8,
        "w": 12,
        "x": 12,
        "y": 0
      },
      "id": 3,
      "options": {
        "legend": {
          "calcs": [],
          "displayMode": "list",
          "placement": "bottom",
          "showLegend": true
        },
        "tooltip": {
          "mode": "single",
          "sort": "none"
        }
      },
      "targets": [
        {
          "expr": "histogram_quantile(0.95, sum(rate(aegismesh_http_request_duration_seconds_bucket[5m])) by (le))",
          "legendFormat": "p95",
          "refId": "A"
        },
        {
          "expr": "histogram_quantile(0.50, sum(rate(aegismesh_http_request_duration_seconds_bucket[5m])) by (le))",
          "legendFormat": "p50",
          "refId": "B"
        }
      ],
      "title": "Backend Latency",
      "type": "timeseries"
    },
    {
      "datasource": {
        "type": "prometheus",
        "uid": "prometheus"
      },
      "fieldConfig": {
        "defaults": {
          "color": {
            "mode": "palette-classic"
          },
          "custom": {
            "axisBorderShow": false,
            "axisCenteredZero": false,
            "axisColorMode": "text",
            "axisLabel": "",
            "axisPlacement": "auto",
            "barAlignment": 0,
            "drawStyle": "line",
            "fillOpacity": 10,
            "gradientMode": "none",
            "hideFrom": {
              "legend": false,
              "tooltip": false,
              "viz": false
            },
            "insertNulls": false,
            "lineInterpolation": "linear",
            "lineWidth": 2,
            "pointSize": 5,
            "scaleDistribution": {
              "type": "linear"
            },
            "showPoints": "never",
            "spanNulls": false,
            "stacking": {
              "group": "A",
              "mode": "none"
            },
            "thresholdsStyle": {
              "mode": "off"
            }
          },
          "mappings": [],
          "unit": "short"
        },
        "overrides": []
      },
      "gridPos": {
        "h": 8,
        "w": 12,
        "x": 0,
        "y": 6
      },
      "id": 4,
      "options": {
        "legend": {
          "calcs": [],
          "displayMode": "list",
          "placement": "bottom",
          "showLegend": true
        },
        "tooltip": {
          "mode": "multi",
          "sort": "none"
        }
      },
      "targets": [
        {
          "expr": "sum by (status_code) (rate(aegismesh_http_requests_total[5m]))",
          "legendFormat": "{{status_code}}",
          "refId": "A"
        }
      ],
      "title": "Requests By Status",
      "type": "timeseries"
    },
    {
      "datasource": {
        "type": "prometheus",
        "uid": "prometheus"
      },
      "fieldConfig": {
        "defaults": {
          "color": {
            "mode": "palette-classic"
          },
          "custom": {
            "axisBorderShow": false,
            "axisCenteredZero": false,
            "axisColorMode": "text",
            "axisLabel": "",
            "axisPlacement": "auto",
            "barAlignment": 0,
            "drawStyle": "line",
            "fillOpacity": 10,
            "gradientMode": "none",
            "hideFrom": {
              "legend": false,
              "tooltip": false,
              "viz": false
            },
            "insertNulls": false,
            "lineInterpolation": "linear",
            "lineWidth": 2,
            "pointSize": 5,
            "scaleDistribution": {
              "type": "linear"
            },
            "showPoints": "never",
            "spanNulls": false,
            "stacking": {
              "group": "A",
              "mode": "none"
            },
            "thresholdsStyle": {
              "mode": "off"
            }
          },
          "mappings": [],
          "unit": "bytes"
        },
        "overrides": []
      },
      "gridPos": {
        "h": 8,
        "w": 12,
        "x": 12,
        "y": 8
      },
      "id": 5,
      "options": {
        "legend": {
          "calcs": [],
          "displayMode": "list",
          "placement": "bottom",
          "showLegend": true
        },
        "tooltip": {
          "mode": "multi",
          "sort": "none"
        }
      },
      "targets": [
        {
          "expr": "aegismesh_nodejs_heap_size_used_bytes",
          "legendFormat": "heap used",
          "refId": "A"
        },
        {
          "expr": "aegismesh_nodejs_heap_size_total_bytes",
          "legendFormat": "heap total",
          "refId": "B"
        }
      ],
      "title": "Node Heap",
      "type": "timeseries"
    },
    {
      "datasource": {
        "type": "postgres",
        "uid": "aegismesh-postgres"
      },
      "fieldConfig": {
        "defaults": {
          "color": {
            "mode": "palette-classic"
          },
          "custom": {
            "axisBorderShow": false,
            "axisCenteredZero": false,
            "axisColorMode": "text",
            "axisLabel": "",
            "axisPlacement": "auto",
            "barAlignment": 0,
            "drawStyle": "bars",
            "fillOpacity": 40,
            "gradientMode": "none",
            "hideFrom": {
              "legend": false,
              "tooltip": false,
              "viz": false
            },
            "insertNulls": false,
            "lineInterpolation": "linear",
            "lineWidth": 1,
            "pointSize": 5,
            "scaleDistribution": {
              "type": "linear"
            },
            "showPoints": "never",
            "spanNulls": false,
            "stacking": {
              "group": "A",
              "mode": "none"
            },
            "thresholdsStyle": {
              "mode": "off"
            }
          },
          "mappings": []
        },
        "overrides": []
      },
      "gridPos": {
        "h": 8,
        "w": 12,
        "x": 0,
        "y": 14
      },
      "id": 6,
      "options": {
        "legend": {
          "calcs": [],
          "displayMode": "list",
          "placement": "bottom",
          "showLegend": true
        },
        "tooltip": {
          "mode": "single",
          "sort": "none"
        }
      },
      "targets": [
        {
          "datasource": {
            "type": "postgres",
            "uid": "aegismesh-postgres"
          },
          "format": "time_series",
          "rawSql": "SELECT\n  $__timeGroup(\"createdAt\", '1h') AS time,\n  COUNT(*) AS audit_events\nFROM \"AuditLog\"\nWHERE $__timeFilter(\"createdAt\")\nGROUP BY time\nORDER BY time;",
          "refId": "A"
        }
      ],
      "title": "Audit Events",
      "type": "timeseries"
    },
    {
      "datasource": {
        "type": "postgres",
        "uid": "aegismesh-postgres"
      },
      "fieldConfig": {
        "defaults": {
          "color": {
            "mode": "palette-classic"
          },
          "custom": {
            "align": "auto",
            "cellOptions": {
              "type": "auto"
            },
            "inspect": false
          },
          "mappings": []
        },
        "overrides": []
      },
      "gridPos": {
        "h": 8,
        "w": 12,
        "x": 12,
        "y": 16
      },
      "id": 7,
      "options": {
        "cellHeight": "sm",
        "footer": {
          "countRows": false,
          "fields": "",
          "reducer": [
            "sum"
          ],
          "show": false
        },
        "showHeader": true
      },
      "pluginVersion": "11.4.0",
      "targets": [
        {
          "datasource": {
            "type": "postgres",
            "uid": "aegismesh-postgres"
          },
          "format": "table",
          "rawSql": "SELECT\n  action,\n  result,\n  category,\n  COUNT(*) AS count\nFROM \"AuditLog\"\nWHERE $__timeFilter(\"createdAt\")\nGROUP BY action, result, category\nORDER BY count DESC\nLIMIT 20;",
          "refId": "A"
        }
      ],
      "title": "Top Audit Actions",
      "type": "table"
    },
    {
      "datasource": {
        "type": "prometheus",
        "uid": "prometheus"
      },
      "gridPos": {
        "h": 6,
        "w": 6,
        "x": 0,
        "y": 22
      },
      "id": 8,
      "targets": [
        {
          "expr": "aegismesh_active_sessions",
          "legendFormat": "active sessions",
          "refId": "A"
        }
      ],
      "title": "Active Sessions",
      "type": "stat"
    },
    {
      "datasource": {
        "type": "prometheus",
        "uid": "prometheus"
      },
      "gridPos": {
        "h": 6,
        "w": 6,
        "x": 6,
        "y": 22
      },
      "id": 9,
      "targets": [
        {
          "expr": "sum(increase(aegismesh_audit_log_writes_total{result=\"failure\"}[1h]))",
          "legendFormat": "failures",
          "refId": "A"
        }
      ],
      "title": "Audit Write Failures",
      "type": "stat"
    },
    {
      "datasource": {
        "type": "prometheus",
        "uid": "prometheus"
      },
      "gridPos": {
        "h": 8,
        "w": 12,
        "x": 12,
        "y": 24
      },
      "id": 10,
      "targets": [
        {
          "expr": "sum by (action, result) (rate(aegismesh_auth_events_total[5m]))",
          "legendFormat": "{{action}} {{result}}",
          "refId": "A"
        }
      ],
      "title": "Authentication Events",
      "type": "timeseries"
    },
    {
      "datasource": {
        "type": "prometheus",
        "uid": "prometheus"
      },
      "gridPos": {
        "h": 8,
        "w": 12,
        "x": 0,
        "y": 28
      },
      "id": 11,
      "targets": [
        {
          "expr": "sum by (action, severity) (rate(aegismesh_security_events_total[5m]))",
          "legendFormat": "{{action}} {{severity}}",
          "refId": "A"
        }
      ],
      "title": "Security Events",
      "type": "timeseries"
    },
    {
      "datasource": {
        "type": "prometheus",
        "uid": "prometheus"
      },
      "gridPos": {
        "h": 8,
        "w": 12,
        "x": 12,
        "y": 32
      },
      "id": 12,
      "targets": [
        {
          "expr": "sum by (action, result) (rate(aegismesh_permission_events_total[5m]))",
          "legendFormat": "{{action}} {{result}}",
          "refId": "A"
        }
      ],
      "title": "Permission Events",
      "type": "timeseries"
    },
    {
      "datasource": {
        "type": "prometheus",
        "uid": "prometheus"
      },
      "gridPos": {
        "h": 8,
        "w": 12,
        "x": 0,
        "y": 36
      },
      "id": 13,
      "targets": [
        {
          "expr": "sum by (action, result) (rate(aegismesh_mfa_events_total[5m]))",
          "legendFormat": "{{action}} {{result}}",
          "refId": "A"
        }
      ],
      "title": "MFA Events",
      "type": "timeseries"
    },
    {
      "datasource": {
        "type": "prometheus",
        "uid": "prometheus"
      },
      "gridPos": {
        "h": 8,
        "w": 12,
        "x": 12,
        "y": 40
      },
      "id": 14,
      "targets": [
        {
          "expr": "sum by (action, result) (rate(aegismesh_api_key_events_total[5m]))",
          "legendFormat": "{{action}} {{result}}",
          "refId": "A"
        }
      ],
      "title": "API Key Events",
      "type": "timeseries"
    },
    {
      "datasource": {
        "type": "prometheus",
        "uid": "prometheus"
      },
      "gridPos": {
        "h": 8,
        "w": 12,
        "x": 0,
        "y": 44
      },
      "id": 15,
      "targets": [
        {
          "expr": "histogram_quantile(0.95, sum(rate(aegismesh_database_query_duration_seconds_bucket[5m])) by (le, model, operation))",
          "legendFormat": "{{model}} {{operation}} p95",
          "refId": "A"
        }
      ],
      "title": "Database Query Latency",
      "type": "timeseries"
    }
  ],
  "preload": false,
  "refresh": "30s",
  "schemaVersion": 40,
  "tags": [
    "aegismesh",
    "iam"
  ],
  "templating": {
    "list": []
  },
  "time": {
    "from": "now-6h",
    "to": "now"
  },
  "timepicker": {},
  "timezone": "browser",
  "title": "AegisMesh Overview",
  "uid": "aegismesh-overview",
  "version": 2,
  "weekStart": ""
}
